tamga/__init__.py
tamga/constants.py
tamga/main.py
tamga/utils/__init__.py
tamga/utils/apprise.py
tamga/utils/colors.py
tamga/utils/time.py
tamga-1.3.1.dist-info/licenses/LICENSE
tamga-1.3.1.dist-info/METADATA
tamga-1.3.1.dist-info/WHEEL
tamga-1.3.1.dist-info/top_level.txt
tamga-1.3.1.dist-info/RECORD
