Metadata-Version: 2.4
Name: tamga
Version: 1.3.1
Summary: A modern, high-performance async logging utility with multiple output formats and colorful console output
Author-email: Doğukan Ürker <dogukanurker@icloud.com>
License: MIT
Project-URL: Homepage, https://tamga.vercel.app/
Project-URL: Documentation, https://tamga.vercel.app/
Project-URL: Source, https://github.com/dogukanurker/tamga/
Project-URL: Bug Tracker, https://github.com/dogukanurker/tamga/issues
Project-URL: Changelog, https://github.com/DogukanUrker/Tamga/releases
Keywords: logging,async,mongodb,colorful,console,file,json,sql,notifications,apprise,performance,buffered,alerting,monitoring,discord,slack,email,sms,webhooks,telegram,modern,high-performance,logger,structured-logging,developer-tools,observability
Classifier: Development Status :: 5 - Production/Stable
Classifier: Intended Audience :: Developers
Classifier: License :: OSI Approved :: MIT License
Classifier: Operating System :: OS Independent
Classifier: Programming Language :: Python :: 3
Classifier: Programming Language :: Python :: 3.7
Classifier: Programming Language :: Python :: 3.8
Classifier: Programming Language :: Python :: 3.9
Classifier: Programming Language :: Python :: 3.10
Classifier: Programming Language :: Python :: 3.11
Classifier: Programming Language :: Python :: 3.12
Classifier: Programming Language :: Python :: 3.13
Classifier: Topic :: System :: Logging
Classifier: Topic :: Software Development :: Libraries :: Python Modules
Requires-Python: >=3.7
License-File: LICENSE
Provides-Extra: mongo
Requires-Dist: pymongo<4.9; extra == "mongo"
Requires-Dist: motor<3.6; extra == "mongo"
Provides-Extra: notifications
Requires-Dist: apprise>=1.9.3; extra == "notifications"
Provides-Extra: all
Requires-Dist: pymongo<4.9; extra == "all"
Requires-Dist: motor<3.6; extra == "all"
Requires-Dist: apprise>=1.9.3; extra == "all"
Dynamic: license-file
